SHRUG_anon/__init__.py
SHRUG_anon/anonalgos.py
SHRUG_anon-1.0.1.dist-info/METADATA
SHRUG_anon-1.0.1.dist-info/WHEEL
SHRUG_anon-1.0.1.dist-info/top_level.txt
SHRUG_anon-1.0.1.dist-info/RECORD
