Metadata-Version: 2.1
Name: SHRUG-anon
Version: 1.0.1
Home-page: https://github.com/gopuman/SHRUG
Author: ['Gopal Nambiar', 'Shreyas Madhav', 'Ruthuvikas Ravikumar']
Author-email: gnambiar@ucdavis.edu
License: MIT
Keywords: Anonymization project
Requires-Dist: scapy
Requires-Dist: yacryptopan
Requires-Dist: numpy
